seam/__init__.py
seam/attributer.py
seam/clusterer.py
seam/compiler.py
seam/identifier.py
seam/meta_explainer.py
seam/seam_gui.py
seam/utils.py
seam/logomaker_batch/__init__.py
seam/logomaker_batch/batch_logo.py
seam/logomaker_batch/colors.py
seam/logomaker_batch/error_handling.py
seam_nn-0.6.5.dist-info/licenses/LICENSE
seam_nn-0.6.5.dist-info/METADATA
seam_nn-0.6.5.dist-info/WHEEL
seam_nn-0.6.5.dist-info/top_level.txt
seam_nn-0.6.5.dist-info/RECORD
