Metadata-Version: 2.4
Name: seam-nn
Version: 0.6.5
Summary: SEAM: Meta-explanations for interpreting sequence-based deep learning models
Home-page: https://github.com/evanseitz/seam-nn
Author: Evan Seitz
Author-email: evan.e.seitz@gmail.com
Classifier: Programming Language :: Python :: 3
Classifier: License :: OSI Approved :: MIT License
Classifier: Operating System :: OS Independent
Requires-Python: >=3.7.2
License-File: LICENSE
Requires-Dist: numpy
Requires-Dist: matplotlib>=3.6.0
Requires-Dist: pandas
Requires-Dist: tqdm
Requires-Dist: psutil
Requires-Dist: biopython
Requires-Dist: tensorflow>=2.0.0
Requires-Dist: scipy>=1.7.0
Requires-Dist: squid-nn
Requires-Dist: seaborn
Provides-Extra: docs
Requires-Dist: sphinx; extra == "docs"
Requires-Dist: sphinx_rtd_theme; extra == "docs"
Provides-Extra: dev
Requires-Dist: pytest; extra == "dev"
Requires-Dist: pytest-cov; extra == "dev"
Requires-Dist: flake8; extra == "dev"
Dynamic: author
Dynamic: author-email
Dynamic: classifier
Dynamic: description
Dynamic: description-content-type
Dynamic: home-page
Dynamic: license-file
Dynamic: provides-extra
Dynamic: requires-dist
Dynamic: requires-python
Dynamic: summary
